qulacs_core.cpython-39-x86_64-linux-gnu.so
qulacs_osaka-0.4.3.dist-info/top_level.txt
qulacs_osaka-0.4.3.dist-info/WHEEL
qulacs_osaka-0.4.3.dist-info/METADATA
qulacs_osaka-0.4.3.dist-info/RECORD
qulacs_osaka-0.4.3.dist-info/LICENSE
qulacs/py.typed
qulacs/circuit.pyi
qulacs/state.pyi
qulacs/observable.pyi
qulacs/gate.pyi
qulacs/__init__.pyi
qulacs/__init__.py
qulacs/quantum_operator.pyi
qulacs/observable/_get_matrix.py
qulacs/observable/py.typed
qulacs/observable/__init__.pyi
qulacs/observable/__init__.py
qulacs/state/py.typed
qulacs/state/__init__.pyi
qulacs/state/__init__.py
qulacs/circuit/py.typed
qulacs/circuit/__init__.pyi
qulacs/circuit/__init__.py
qulacs/quantum_operator/py.typed
qulacs/quantum_operator/__init__.pyi
qulacs/quantum_operator/__init__.py
qulacs/gate/py.typed
qulacs/gate/__init__.pyi
qulacs/gate/__init__.py
qulacs/utils/conversions_openfermion.py
qulacs/utils/__init__.py
qulacs/vistest/test_vis.py
qulacs/vistest/__init__.py
qulacs/visualizer/visualizer.py
qulacs/visualizer/__init__.py
qulacs_osaka.libs/libgomp-a34b3233.so.1.0.0
