Metadata-Version: 2.1
Name: qulacs-osaka
Version: 0.4.3
Summary: Quantum circuit simulator for research
Home-page: http://www.qulacs.org
Author: QunaSys
Author-email: qulacs@qunasys.com
Classifier: Development Status :: 3 - Alpha
Classifier: Environment :: Console
Classifier: Intended Audience :: Science/Research
Classifier: License :: OSI Approved :: MIT License
Classifier: Operating System :: MacOS :: MacOS X
Classifier: Operating System :: Microsoft :: Windows
Classifier: Operating System :: POSIX
Classifier: Programming Language :: Python
Classifier: Topic :: Communications :: Email
License-File: LICENSE
